imgflip/__init__.py
imgflip/__main__.py
imgflip/errors.py
imgflip/models.py
imgflip/objects.py
imgflip.py-1.0.dist-info/LICENSE
imgflip.py-1.0.dist-info/METADATA
imgflip.py-1.0.dist-info/WHEEL
imgflip.py-1.0.dist-info/top_level.txt
imgflip.py-1.0.dist-info/RECORD
