Metadata-Version: 2.1
Name: imgflip.py
Version: 1.0
Summary: Create memes using imgflip easily!
Home-page: https://github.com/SYCKGit/imgflip.py
Author: SYCK
Author-email: oviyangandhi@gmail.com
License: MIT
Project-URL: Documentation, https://imgflip.readthedocs.io/
Platform: UNKNOWN
Classifier: Programming Language :: Python :: 3
Classifier: License :: OSI Approved :: MIT License
Classifier: Operating System :: OS Independent
Requires-Python: >=3.8
License-File: LICENSE
Requires-Dist: aiohttp
Requires-Dist: requests
